wdl_parser/__init__.py
wdl_parser/development.py
wdl_parser/draft_2.py
wdl_parser/draft_3.py
wdl_parser/version_1_0.py
wdl_parser-0.0.3.dist-info/LICENSE
wdl_parser-0.0.3.dist-info/METADATA
wdl_parser-0.0.3.dist-info/WHEEL
wdl_parser-0.0.3.dist-info/top_level.txt
wdl_parser-0.0.3.dist-info/RECORD
