Metadata-Version: 2.1
Name: wdl-parser
Version: 0.0.3
Summary: Python package, containing Python parsers for the Broad's WDL language
Home-page: https://github.com/TMiguelT/WdlParserPackaging
Maintainer: TMiguelT
Maintainer-email: ttmigueltt@gmail.com
License: GPL
Platform: UNKNOWN
